VCIBD2/takeCommand.py
VCIBD2-2.0.0.dist-info/LICENCE
VCIBD2-2.0.0.dist-info/METADATA
VCIBD2-2.0.0.dist-info/WHEEL
VCIBD2-2.0.0.dist-info/top_level.txt
VCIBD2-2.0.0.dist-info/RECORD
